lzhnet/__init__.py
lzhnet/chrome.py
lzhnet/mail.py
lzhnet/ssh.py
lzhnet-25.0.0.dist-info/METADATA
lzhnet-25.0.0.dist-info/WHEEL
lzhnet-25.0.0.dist-info/top_level.txt
lzhnet-25.0.0.dist-info/RECORD
