Metadata-Version: 2.4
Name: lzhnet
Version: 25.0.0
Author-email: zhlei <leizuoho@mail.ustc.edu.cn>
Requires-Python: >=3.10
Requires-Dist: scipy
